odoo/addons/helpdesk_mgmt_sla/README.rst
odoo/addons/helpdesk_mgmt_sla/__init__.py
odoo/addons/helpdesk_mgmt_sla/__manifest__.py
odoo/addons/helpdesk_mgmt_sla/demo/helpdesk_mgmt_sla_demo.xml
odoo/addons/helpdesk_mgmt_sla/i18n/es.po
odoo/addons/helpdesk_mgmt_sla/i18n/es_AR.po
odoo/addons/helpdesk_mgmt_sla/i18n/helpdesk_mgmt_sla.pot
odoo/addons/helpdesk_mgmt_sla/i18n/it.po
odoo/addons/helpdesk_mgmt_sla/i18n/pt.po
odoo/addons/helpdesk_mgmt_sla/i18n/tr.po
odoo/addons/helpdesk_mgmt_sla/migrations/18.0.2.0.0/post-migration.py
odoo/addons/helpdesk_mgmt_sla/models/__init__.py
odoo/addons/helpdesk_mgmt_sla/models/helpdesk_sla.py
odoo/addons/helpdesk_mgmt_sla/models/helpdesk_sla_report.py
odoo/addons/helpdesk_mgmt_sla/models/helpdesk_ticket.py
odoo/addons/helpdesk_mgmt_sla/models/helpdesk_ticket_sla.py
odoo/addons/helpdesk_mgmt_sla/models/helpdesk_ticket_team.py
odoo/addons/helpdesk_mgmt_sla/readme/CONFIGURE.md
odoo/addons/helpdesk_mgmt_sla/readme/CONTRIBUTORS.md
odoo/addons/helpdesk_mgmt_sla/readme/DESCRIPTION.md
odoo/addons/helpdesk_mgmt_sla/readme/USAGE.md
odoo/addons/helpdesk_mgmt_sla/security/helpdesk_sla_security.xml
odoo/addons/helpdesk_mgmt_sla/security/ir.model.access.csv
odoo/addons/helpdesk_mgmt_sla/static/description/icon.png
odoo/addons/helpdesk_mgmt_sla/static/description/index.html
odoo/addons/helpdesk_mgmt_sla/tests/__init__.py
odoo/addons/helpdesk_mgmt_sla/tests/common.py
odoo/addons/helpdesk_mgmt_sla/tests/test_helpdesk_mgmt_sla.py
odoo/addons/helpdesk_mgmt_sla/views/helpdesk_sla_report.xml
odoo/addons/helpdesk_mgmt_sla/views/helpdesk_sla_views.xml
odoo/addons/helpdesk_mgmt_sla/views/helpdesk_ticket_sla.xml
odoo/addons/helpdesk_mgmt_sla/views/helpdesk_ticket_team_views.xml
odoo/addons/helpdesk_mgmt_sla/views/helpdesk_ticket_views.xml
odoo_addon_helpdesk_mgmt_sla-18.0.2.1.0.2.dist-info/METADATA
odoo_addon_helpdesk_mgmt_sla-18.0.2.1.0.2.dist-info/WHEEL
odoo_addon_helpdesk_mgmt_sla-18.0.2.1.0.2.dist-info/top_level.txt
odoo_addon_helpdesk_mgmt_sla-18.0.2.1.0.2.dist-info/RECORD
